countrypy/__init__.py
countrypy/ascii_art.py
countrypy/cli.py
countrypy/country_data.py
countrypy-1.1.0.dist-info/LICENSE
countrypy-1.1.0.dist-info/METADATA
countrypy-1.1.0.dist-info/WHEEL
countrypy-1.1.0.dist-info/entry_points.txt
countrypy-1.1.0.dist-info/top_level.txt
countrypy-1.1.0.dist-info/RECORD
