Metadata-Version: 2.1
Name: countrypy
Version: 1.1.0
Summary: A modern Python library for country data
Author-email: Arjun Sharda <sharda.aj17@gmail.com>
License: MIT License
Project-URL: Homepage, https://github.com/ArjunSharda/countrypy
Project-URL: Bug Tracker, https://github.com/ArjunSharda/countrypy/issues
Keywords: country,languages,nation,currency,world,lightweight,efficient
Classifier: Programming Language :: Python :: 3
Classifier: Programming Language :: Python :: 3.7
Classifier: Programming Language :: Python :: 3.8
Classifier: Programming Language :: Python :: 3.9
Classifier: Programming Language :: Python :: 3.10
Classifier: License :: OSI Approved :: MIT License
Classifier: Operating System :: OS Independent
Requires-Python: >=3.7
License-File: LICENSE
